
<map name="atl_map">
<area alt="" coords="62,185,351,283" href="atl_central.html">
<area alt="" coords="123,298,385,575" href="atl_south.html">
<area alt="" coords="272,596,405,446" href="atl_south.html">
<area alt="" coords="386,425,463,442" href="ind_map.html">
<area alt="" coords="37,368,120,385" href="pac_map.html">
<area alt="" coords="173,576,268,593" href="sou_map.html">
<area alt="" coords="122,29,351,179" href="atl_north.html">
</map>
<img src="atl_map.jpg" width="506" height="621" border="0" usemap="#atl_map">
<br>
<b>Click on any region</b>
